[
  {
    "id": "SJKhIAKYB",
    "from": "system",
    "text": "Welcome!"
  },
  {
    "id": "eg4LbKP1dU_VNeZYGV7DB",
    "from": "alice",
    "text": "Hi"
  },
  {
    "id": "x0OFTFyWDC-u-rTj9uYMD",
    "from": "alice",
    "text": "i love u"
  },
  {
    "id": "LIzvDche8lxLnwv-QhJzd",
    "from": "alice",
    "text": "lala"
  },
  {
    "id": "PahKDutiI3RrWTWiKzgFO",
    "from": "alice",
    "text": "tinh oi"
  },
  {
    "id": "teqcM8Y_Lt6CWcj6YzZg8",
    "from": "alice",
    "text": "dang lam gi do"
  },
  {
    "id": "SrxHk3C409uOQWvD3Ni7o",
    "from": "bob",
    "text": "anyone?"
  },
  {
    "id": "xPOXGmIodNHfWlEZw8CUj",
    "from": "alice",
    "text": "i'm here"
  },
  {
    "id": "9QoNTXE0dQFjnrSazmV8U",
    "from": "alice",
    "text": "hi"
  },
  {
    "id": "fBsxsePNLAiaxMXhwo-gA",
    "from": "alice",
    "text": "hello"
  },
  {
    "id": "upaUImVplWxizKgKIz-Ru",
    "from": "alice",
    "text": "haha"
  },
  {
    "id": "zNsxTMYkHEquOdbqUih72",
    "from": "alice",
    "text": "tinnh oi"
  },
  {
    "id": "wB7eDCyWFR_dFbFlH9gOq",
    "from": "alice",
    "text": "nho ban qua"
  },
  {
    "id": "El5FBWnoiFzp5Pu9vSOJI",
    "from": "alice",
    "text": "what sup"
  },
  {
    "id": "onNXIU4OcwKUC_WLmA2aV",
    "from": "alice",
    "text": "hey"
  },
  {
    "id": "cTyB30LQ6LK6gHFITAA-w",
    "from": "alice",
    "text": "lam gi vay"
  },
  {
    "id": "bBWq49VWD8yH30VyBk6O2",
    "from": "alice",
    "text": "cha lam gi ca"
  },
  {
    "id": "alSgivaKK7IrvvuOGFgTc",
    "from": "alice",
    "text": "nhu nao"
  },
  {
    "id": "Am9rvUlI7NjrozxbtLtic",
    "from": "alice",
    "text": "hay lam"
  },
  {
    "id": "oN23mEswwYQBCRZmKdP24",
    "from": "alice",
    "text": "asdf"
  },
  {
    "id": "r5dQFlWNwPf4_YnTPGhVi",
    "from": "alice",
    "text": "anybody"
  },
  {
    "id": "IZMRLgoc0M5nGQHMMpRlM",
    "from": "alice",
    "text": "ping"
  },
  {
    "id": "vhTM0Qb4OAIBE9gLESfyb",
    "from": "charlie",
    "text": "i'm charlie"
  },
  {
    "id": "VjoE2HTGFHilfcai6z3WD",
    "from": "charlie",
    "text": "i'm alice"
  },
  {
    "id": "Wqx04scMXbUVTrqdXNNQU",
    "from": "charlie",
    "text": "hello"
  },
  {
    "id": "NfO7QYxBC2DzTFCCchmYu",
    "from": "bob",
    "text": "i'm bob"
  },
  {
    "id": "f10WlC64PQbEwVxdoR2lJ",
    "from": "alice",
    "text": "i'm charlie"
  },
  {
    "id": "-ixGyoaXIv-kGKhvAfxnN",
    "from": "alice",
    "text": "hi"
  },
  {
    "id": "4ZH8OMAeky9e9_ZnxB3SQ",
    "from": "alice",
    "text": "h"
  }
]